Verilog/lab2_handshake/rtl/basic.v
//==============================================================================
// File name    : basic.v
// Description  : [Brief description of what this module does]
//
// Author       : [Jeongyoon Kang]
// Email        : [goneki9713@naver.com]
// Date         : 2025-12-13
// Version      : 1.0
//
// History:
//   2025-12-13 - [Jeongyoon Kang] - Initial version: Simple Vaild interface example
//
// Parameters:
//   PARAM_NAME  - [Description]
//
// Notes:
//   - [Any important notes about this module]
//   - [Design decisions, limitations, or usage guidelines]
//==============================================================================

`timescale 1ns/1ps
`default_nettype none

module power #(
    parameter DATA_WIDTH = 32
)(
    // Clock and Reset
    input  wire                     clk,
    input  wire                     reset_n,

    // Input Interface
    input  wire                     s_valid,
    input  wire  [DATA_WIDTH-1:0]   s_data,
    output wire                     s_ready,
    // Output Interface
    input wire                      m_ready, 
    output wire                     m_valid,
    output wire  [63:0]   m_data
);

//🟩: Stage
//🟧: Combinational logic
//🟦: Sequential logic


//=============================================================================
// Internal Signal Declarations
//=============================================================================

//-----------------------------------------------------------------------------
// 🟩Stage 0
//-----------------------------------------------------------------------------
// 🟧Combinational signals (intermediate values, NOT registers)

    wire [63:0] power_of_2;
    wire        hs;


// 🟦Sequential signals (actual flip-flops)

    reg [2:0] r_valid;
    reg [63:0] r_power_of_2;

//-----------------------------------------------------------------------------
// 🟩Stage 1
//-----------------------------------------------------------------------------
// 🟧Combinational signals (intermediate values, NOT registers)

    wire [63:0] power_of_4;

// 🟦Sequential signals (actual flip-flops)

    // reg [2:0] r_valid;
    reg [63:0] r_power_of_4;

//-----------------------------------------------------------------------------
// 🟩Stage 2
//-----------------------------------------------------------------------------
// 🟧Combinational signals (intermediate values, NOT registers)

    wire [63:0] power_of_8;

// 🟦Sequential signals (actual flip-flops)

    // reg [2:0] r_valid;
    reg [63:0] r_power_of_8;



//=============================================================================
// 🟧Combinational Logic
//=============================================================================

// 🟩Stage 0
    assign hs = m_valid & m_ready;
    assign power_of_2 = s_data * s_data;
    assign s_ready = !m_valid | m_ready; // Ready when output is ready to accept new data;

// 🟩Stage 1

    assign power_of_4 = r_power_of_2 * r_power_of_2;


// 🟩Stage 2

    assign power_of_8 = r_power_of_4 * r_power_of_4;


//=============================================================================
// 🟦Sequential Logic (Registers)
//=============================================================================

// 🟩Stage 0

    //
    always@(posedge clk or negedge reset_n)begin
        if(!reset_n)begin
            r_valid[0] <= 1'b0; 
        end 
        else if(s_ready)begin
            r_valid[0] <= s_valid;
        end
    end

    always@(posedge clk or negedge reset_n)begin
        if(!reset_n)begin
            r_power_of_2 <= 'b0;
        end
        else if(s_ready)begin
            r_power_of_2 <= power_of_2;
        end
    end


// 🟩Stage 1

    always@(posedge clk or negedge reset_n)begin
        if(!reset_n)begin
            r_valid[1] <= 1'b0;
        end
        else if(s_ready)begin
            r_valid[1] <= r_valid[0];
        end
    end

    always@(posedge clk or negedge reset_n)begin
        if(!reset_n)begin
            r_power_of_4 <= 'b0;
        end
        else if(s_ready)begin
            r_power_of_4 <= power_of_4;
        end
    end


// 🟩Stage 2

    always@(posedge clk or negedge reset_n)begin
        if(!reset_n)begin
            r_valid[2] <= 1'b0;
        end
        else if(s_ready)begin
            r_valid[2] <= r_valid[1];
        end
    end

    always@(posedge clk or negedge reset_n)begin
        if(!reset_n)begin
            r_power_of_8 <= 'b0;
        end
        else if(s_ready)begin
            r_power_of_8 <= power_of_8;
        end
    end



//=============================================================================
// Output Assign(Must be registered output!)
//=============================================================================

    assign m_valid = r_valid[2];
    assign m_data = r_power_of_8;


//=============================================================================
// Assertions (for simulation/formal verification)
//=============================================================================
`ifdef FORMAL
    // Add formal properties here
`endif

`ifdef SIMULATION
    // Add simulation assertions here
`endif

endmodule

`default_nettype wire

Verilog/lab2_handshake/testbench/basic_tb.v
//==============================================================================
// File name    : basic_tb.v
// Description  : Testbench for power-of-8 module (basic.v)
//
// Author       : [Jeongyoon Kang]
// Email        : [goneki9713@naver.com]
// Date         : 2025-12-13
// Version      : 1.0
//
// History:
//   2025-12-13 - [Jeongyoon Kang] - Initial version
//
// Test Cases:
//   1. Test vector verification using reference input/output files
//
// Notes:
//   - Reads test vectors from ref/input.txt
//   - Compares DUT output with ref/output.txt
//==============================================================================

`timescale 1ns/1ps
`default_nettype none

module basic_tb;

//=============================================================================
// Parameters
//=============================================================================
parameter DATA_WIDTH = 8;
parameter CLK_PERIOD = 10;  // 100MHz clock
parameter NUM_TESTS  = 1000; // Number of test vectors


//=============================================================================
// Clock and Reset Generation
//=============================================================================
reg clk;
reg reset_n;

// Clock generation
initial begin
    clk = 0;
    forever #(CLK_PERIOD/2) clk = ~clk;
end

// Reset generation
initial begin
    reset_n = 0;
    repeat(20)begin
        @(posedge clk);
    end
    reset_n = 1;
    $display("[%0t] Reset released", $time);
end


//=============================================================================
// DUT Interface Signals
//=============================================================================

// Input Interface
reg                     m_valid_tb;
reg  [DATA_WIDTH-1:0]   m_data_tb;
wire                    m_ready_tb;


// Output Interface
wire                    s_valid_tb;
wire [63:0]             s_data_tb;
reg                     s_ready_tb;

reg [63:0] ref_data;

//=============================================================================
// DUT Instantiation
//=============================================================================
power #(
    .DATA_WIDTH(DATA_WIDTH)
) u_dut (
    .clk        (clk),
    .reset_n    (reset_n),

    .s_valid    (m_valid_tb),
    .s_data     (m_data_tb),
    .s_ready    (m_ready_tb),

    .m_ready    (s_ready_tb),
    .m_valid    (s_valid_tb),
    .m_data     (s_data_tb)
);


//=============================================================================
// Test Control Variables
//=============================================================================
integer test_count;
integer pass_count;
integer fail_count;

//=============================================================================
// Test Vector Storage
//=============================================================================
//
// Test Vector Range: 0 to 255
//
// This power-of-8 module outputs 64-bit results. To prevent overflow in the
// 64-bit output (2^64 - 1 max), the input must satisfy input^8 <= 2^64 - 1.
// Solving for the input gives a maximum value of (2^64 - 1)^(1/8) ≈ 255.
// As a result, all test vectors are generated in the range [0, 255].
//
reg [DATA_WIDTH-1:0] input_vectors  [0:NUM_TESTS-1];
reg [63:0]           output_vectors [0:NUM_TESTS-1];


//=============================================================================
// Load Test Vectors from Files
//=============================================================================
integer input_file, output_file;
integer scan_result;
integer idx;
reg vectors_loaded;
integer handshake_monitor_enable = 0;

initial begin
    vectors_loaded = 0;

    // Read input vectors (decimal format)
    input_file = $fopen("testbench/ref/input.txt", "r");
    if (input_file == 0) begin
        $display("[ERROR] Cannot open input.txt");
        $finish;
    end

    idx = 0;
    while (!$feof(input_file) && idx < NUM_TESTS) begin
        scan_result = $fscanf(input_file, "%d\n", input_vectors[idx]);
        if (scan_result == 1) idx = idx + 1;
    end
    $fclose(input_file);
    $display("[INFO] Loaded %0d input vectors", idx);

    // Read output vectors (decimal format)
    output_file = $fopen("testbench/ref/output.txt", "r");
    if (output_file == 0) begin
        $display("[ERROR] Cannot open output.txt");
        $finish;
    end

    idx = 0;
    while (!$feof(output_file) && idx < NUM_TESTS) begin
        scan_result = $fscanf(output_file, "%d\n", output_vectors[idx]);
        if (scan_result == 1) idx = idx + 1;
    end
    $fclose(output_file);
    $display("[INFO] Loaded %0d output vectors", idx);

    vectors_loaded = 1;
end


//=============================================================================
// Initial Setup
//=============================================================================
initial begin
    // Initialize test counters
    test_count = 0;
    pass_count = 0;
    fail_count = 0;

    // Initialize signals
    m_valid_tb = 0;
    m_data_tb  = 0;
    s_ready_tb = 0;

    // Wait for vectors to be loaded
    wait(vectors_loaded == 1);

    // Wait for reset
    wait(reset_n == 1);
    @(posedge clk);

    // Run test
    test_continuous_flow();

    // Display results
    #(CLK_PERIOD*10);
    display_test_summary();

    $finish;
end


//=============================================================================
// Task: Check Result
//=============================================================================
task check_result;
    input [63:0] expected;
    input [63:0] actual;
    input integer test_id;
    input [DATA_WIDTH-1:0] input_val;
    begin
        test_count = test_count + 1;
        if (expected == actual) begin
            pass_count = pass_count + 1;
            if (test_id % 100 == 0) begin  // Print every 100th test
                $display("[PASS] Test %0d: input=%0d, output=%0d", test_id, input_val, actual);
            end
        end else begin
            fail_count = fail_count + 1;
            $display("[FAIL] Test %0d: input=%0d", test_id, input_val);
            $display("       Expected: %0d (0x%h), Got: %0d (0x%h)", expected, expected, actual, actual);
        end
    end
endtask


//=============================================================================
// Test Case: Continuous Flow Test
//=============================================================================
task test_continuous_flow;
    integer cycle_cnt;
    integer input_idx;
    integer output_idx;
    integer max_cycles;
    begin
        $display("\n========================================");
        $display("  Testing Continuous Data Flow");
        $display("========================================\n");

        handshake_monitor_enable = 1;

        input_idx = 0;
        output_idx = 0;
        max_cycles = 20000;

        // m_valid_tb = 0;
        // m_data_tb = 0;
        // s_ready_tb = 1;

        m_valid_tb <= 0;
        m_data_tb <= 0;
        s_ready_tb <= 1;

        for (cycle_cnt = 0; cycle_cnt < max_cycles; cycle_cnt = cycle_cnt + 1) begin
            // Update input data before clock edge
            if (input_idx < NUM_TESTS) begin
                m_valid_tb <= 1;
                m_data_tb <= input_vectors[input_idx];
            end else begin
                m_valid_tb <= 0;
            end

            @(posedge clk);

            // Check input handshake
            if (m_valid_tb && m_ready_tb && input_idx < NUM_TESTS) begin
                input_idx = input_idx + 1;
            end

            // Check output handshake
            if (s_valid_tb && s_ready_tb && output_idx < NUM_TESTS) begin
                check_result(output_vectors[output_idx], s_data_tb, output_idx, input_vectors[output_idx]);
                ref_data <= output_vectors[output_idx];
                output_idx = output_idx + 1;
            end

            // Exit when done
            if (output_idx >= NUM_TESTS) begin
                break;
            end
        end

        m_valid_tb <= 0;
        s_ready_tb <= 0;

        $display("\n========================================");
        $display("  Test completed in %0d cycles", cycle_cnt);
        $display("  Sent %0d/%0d inputs", input_idx, NUM_TESTS);
        $display("  Received %0d/%0d outputs", output_idx, NUM_TESTS);
        $display("========================================\n");
    end
endtask


//=============================================================================
// Display Test Summary
//=============================================================================
task display_test_summary;
    begin
        $display("\n");
        $display("========================================");
        $display("       TEST SUMMARY");
        $display("========================================");
        $display("Total Tests : %0d", test_count);
        $display("Passed      : %0d", pass_count);
        $display("Failed      : %0d", fail_count);
        $display("========================================");

        if (fail_count == 0) begin
            $display("✓ ALL TESTS PASSED!");
        end else begin
            $display("✗ SOME TESTS FAILED!");
        end
        $display("========================================\n");
    end
endtask


//=============================================================================
// Waveform Dump (for GTKWave, Verdi, etc.)
//=============================================================================
initial begin
    $dumpfile("basic_tb.vcd");
    $dumpvars(0, basic_tb);
end


//=============================================================================
// Handshake Monitor
//=============================================================================

always @(posedge clk) begin
    if (reset_n && handshake_monitor_enable) begin
        // Monitor input handshake (upstream -> DUT)
        if (m_valid_tb && m_ready_tb) begin
            $display("[%0t] [UPSTREAM->DUT] Handshake OK, Data=%0d accepted by DUT", $time, m_data_tb);
        end else if (m_valid_tb && !m_ready_tb) begin
            $display("[%0t] [UPSTREAM STALL] DUT not ready (m_ready=0), Data=%0d waiting", $time, m_data_tb);
        end

        // Monitor output handshake (DUT -> downstream)
        if (s_valid_tb && s_ready_tb) begin
            $display("[%0t] [DUT->DOWNSTREAM] Handshake OK, Data=%0d accepted by downstream", $time, s_data_tb);
        end else if (s_valid_tb && !s_ready_tb) begin
            $display("[%0t] [DOWNSTREAM STALL] Downstream not ready (s_ready=0), Data=%0d waiting", $time, s_data_tb);
        end
    end
end


//=============================================================================
// Timeout Watchdog
//=============================================================================
// initial begin
//     #(CLK_PERIOD*10000);  // Adjust timeout as needed
//     $display("\n[ERROR] Simulation timeout!");
//     display_test_summary();
//     $finish;
// end


//=============================================================================
// Assertions (SystemVerilog style - comment out if using Verilog)
//=============================================================================
`ifdef SIMULATION
    // Check for X/Z values on critical signals
    always @(posedge clk) begin
        if (reset_n) begin
            if (^s_valid_tb === 1'bx) $display("[WARNING] s_valid_tb has X/Z values at time %0t", $time);
            if (^o_valid === 1'bx) $display("[WARNING] o_valid has X/Z values at time %0t", $time);
        end
    end
`endif

endmodule

`default_nettype wire

Verilog/lab2_handshake/basic_tb.vcd
$date
   Sat Dec 27 19:18:13 2025
$end

$version
  2025.2
  $dumpfile ("basic_tb.vcd") 
$end

$timescale
  1ps
$end

$scope module basic_tb $end
$var reg 1 ! clk $end
$var reg 1 " reset_n $end
$var reg 1 # m_valid_tb $end
$var reg 8 $ m_data_tb [7:0] $end
$var wire 1 % m_ready_tb $end
$var wire 1 & s_valid_tb $end
$var wire 64 ' s_data_tb [63:0] $end
$var reg 1 ( s_ready_tb $end
$var reg 64 ) ref_data [63:0] $end
$var integer 32 * test_count [31:0] $end
$var integer 32 + pass_count [31:0] $end
$var integer 32 , fail_count [31:0] $end
$var integer 32 - input_file [31:0] $end
$var integer 32 . output_file [31:0] $end
$var integer 32 / scan_result [31:0] $end
$var integer 32 0 idx [31:0] $end
$var reg 1 1 vectors_loaded $end
$var integer 32 2 handshake_monitor_enable [31:0] $end
$scope module u_dut $end
$var wire 1 3 clk $end
$var wire 1 4 reset_n $end
$var wire 1 5 s_valid $end
$var wire 8 6 s_data [7:0] $end
$var wire 1 % s_ready $end
$var wire 1 7 m_ready $end
$var wire 1 & m_valid $end
$var wire 64 ' m_data [63:0] $end
$var wire 64 8 power_of_2 [63:0] $end
$var wire 1 9 hs $end
$var reg 3 : r_valid [2:0] $end
$var reg 64 ; r_power_of_2 [63:0] $end
$var wire 64 < power_of_4 [63:0] $end
$var reg 64 = r_power_of_4 [63:0] $end
$var wire 64 > power_of_8 [63:0] $end
$var reg 64 ? r_power_of_8 [63:0] $end
$upscope $end
$scope task check_result $end
$var reg 64 @ expected [63:0] $end
$var reg 64 A actual [63:0] $end
$var integer 32 B test_id [31:0] $end
$var reg 8 C input_val [7:0] $end
$upscope $end
$scope task test_continuous_flow $end
$var integer 32 D cycle_cnt [31:0] $end
$var integer 32 E input_idx [31:0] $end
$var integer 32 F output_idx [31:0] $end
$var integer 32 G max_cycles [31:0] $end
$upscope $end
$scope task display_test_summary $end
$upscope $end
$upscope $end
$enddefinitions $end

#0
$dumpvars
0!
0"
0#
b0 $
1%
0&
b0 '
0(
bx )
b0 *
b0 +
b0 ,
b11111111111111111011000111100000 -
b11111111111111111011000111100000 .
b1 /
b1111101000 0
11
b0 2
03
04
05
b0 6
07
b0 8
09
b0 :
b0 ;
b0 <
b0 =
b0 >
b0 ?
bx @
bx A
bx B
bx C
bx D
bx E
bx F
bx G
$end

#5000
1!
13

#10000
0!
03

#15000
1!
13

#20000
0!
03

#25000
1!
13

#30000
0!
03

#35000
1!
13

#40000
0!
03

#45000
1!
13

#50000
0!
03

#55000
1!
13

#60000
0!
03

#65000
1!
13

#70000
0!
03

#75000
1!
13

#80000
0!
03

#85000
1!
13

#90000
0!
03

#95000
1!
13

#100000
0!
03

#105000
1!
13

#110000
0!
03

#115000
1!
13

#120000
0!
03

#125000
1!
13

#130000
0!
03

#135000
1!
13

#140000
0!
03

#145000
1!
13

#150000
0!
03

#155000
1!
13

#160000
0!
03

#165000
1!
13

#170000
0!
03

#175000
1!
13

#180000
0!
03

#185000
1!
13

#190000
0!
03

#195000
1!
1"
13
14

#200000
0!
03

#205000
1!
1#
b11001111 $
1(
b1 2
13
15
b11001111 6
17
b1010011101100001 8
b0 D
b0 E
b0 F
b100111000100000 G

#210000
0!
03

#215000
1!
b111101 $
13
b111101 6
b111010001001 8
b1 :
b1010011101100001 ;
b1101101011011111011001011000001 <
b1 D
b1 E

#220000
0!
03

#225000
1!
b1011011 $
13
b1011011 6
b10000001011001 8
b11 :
b111010001001 ;
b110100110100010101010001 <
b1101101011011111011001011000001 =
b10111011001000010011101111010011011010001011101111010110000001 >
b10 D
b10 E

#230000
0!
03

#235000
1!
b1100110 $
1&
b10111011001000010011101111010011011010001011101111010110000001 '
13
b1100110 6
b10100010100100 8
19
b111 :
b10000001011001 ;
b100000101100101111011110001 <
b110100110100010101010001 =
b101011100101101101010110010010101100001110100001 >
b10111011001000010011101111010011011010001011101111010110000001 ?
b11 D
b11 E

#240000
0!
03

#245000
1!
b11111011 $
b101011100101101101010110010010101100001110100001 '
b10111011001000010011101111010011011010001011101111010110000001 )
b1 *
b1 +
13
b11111011 6
b1111011000011001 8
b10100010100100 ;
b110011100111010100100010000 <
b100000101100101111011110001 =
b10000101101001110101111111100101000011101111011100001 >
b101011100101101101010110010010101100001110100001 ?
b10111011001000010011101111010011011010001011101111010110000001 @
b10111011001000010011101111010011011010001011101111010110000001 A
b0 B
b11001111 C
b100 D
b100 E
b1 F

#250000
0!
03

#255000
1!
b100010 $
b10000101101001110101111111100101000011101111011100001 '
b101011100101101101010110010010101100001110100001 )
b10 *
b10 +
13
b100010 6
b10010000100 8
b1111011000011001 ;
b11101100100101000000111001110001 <
b110011100111010100100010000 =
b101001101000000010111000010100000001100010000100000000 >
b10000101101001110101111111100101000011101111011100001 ?
b101011100101101101010110010010101100001110100001 @
b101011100101101101010110010010101100001110100001 A
b1 B
b111101 C
b101 D
b101 E
b10 F

#260000
0!
03

#265000
1!
b1100110 $
b101001101000000010111000010100000001100010000100000000 '
b10000101101001110101111111100101000011101111011100001 )
b11 *
b11 +
13
b1100110 6
b10100010100100 8
b10010000100 ;
b101000110010000010000 <
b11101100100101000000111001110001 =
b1101101010100001010100000100000100001011011110001000110111100001 >
b101001101000000010111000010100000001100010000100000000 ?
b10000101101001110101111111100101000011101111011100001 @
b10000101101001110101111111100101000011101111011100001 A
b10 B
b1011011 C
b110 D
b110 E
b11 F

#270000
0!
03

#275000
1!
b10100101 $
b1101101010100001010100000100000100001011011110001000110111100001 '
b101001101000000010111000010100000001100010000100000000 )
b100 *
b100 +
13
b10100101 6
b110101001011001 8
b10100010100100 ;
b110011100111010100100010000 <
b101000110010000010000 =
b11001111111001001100111001000000100000000 >
b1101101010100001010100000100000100001011011110001000110111100001 ?
b101001101000000010111000010100000001100010000100000000 @
b101001101000000010111000010100000001100010000100000000 A
b11 B
b1100110 C
b111 D
b111 E
b100 F

#280000
0!
03

#285000
1!
b10110011 $
b11001111111001001100111001000000100000000 '
b1101101010100001010100000100000100001011011110001000110111100001 )
b101 *
b101 +
13
b10110011 6
b111110100101001 8
b110101001011001 ;
b101100001011011101001011110001 <
b110011100111010100100010000 =
b101001101000000010111000010100000001100010000100000000 >
b11001111111001001100111001000000100000000 ?
b1101101010100001010100000100000100001011011110001000110111100001 @
b1101101010100001010100000100000100001011011110001000110111100001 A
b100 B
b11111011 C
b1000 D
b1000 E
b101 F

#290000
0!
03

#295000
1!
b1000 $
b101001101000000010111000010100000001100010000100000000 '
b11001111111001001100111001000000100000000 )
b110 *
b110 +
13
b1000 6
b1000000 8
b111110100101001 ;
b111101001100010001000010010001 <
b101100001011011101001011110001 =
b11110011111110010001011011010101110100010100100011011100001 >
b101001101000000010111000010100000001100010000100000000 ?
b11001111111001001100111001000000100000000 @
b11001111111001001100111001000000100000000 A
b101 B
b100010 C
b1001 D
b1001 E
b110 F

#300000
0!
03

#305000
1!
b111110 $
b11110011111110010001011011010101110100010100100011011100001 '
b101001101000000010111000010100000001100010000100000000 )
b111 *
b111 +
13
b111110 6
b111100000100 8
b1000000 ;
b1000000000000 <
b111101001100010001000010010001 =
b111010100000011010110100110001110010100101000111001000100001 >
b11110011111110010001011011010101110100010100100011011100001 ?
b101001101000000010111000010100000001100010000100000000 @
b101001101000000010111000010100000001100010000100000000 A
b110 B
b1100110 C
b1010 D
b1010 E
b111 F

#310000
0!
03

#315000
1!
b10010001 $
b111010100000011010110100110001110010100101000111001000100001 '
b11110011111110010001011011010101110100010100100011011100001 )
b1000 *
b1000 +
13
b10010001 6
b101001000100001 8
b111100000100 ;
b111000010111100000010000 <
b1000000000000 =
b1000000000000000000000000 >
b111010100000011010110100110001110010100101000111001000100001 ?
b11110011111110010001011011010101110100010100100011011100001 @
b11110011111110010001011011010101110100010100100011011100001 A
b111 B
b10100101 C
b1011 D
b1011 E
b1000 F

#320000
0!
03

#325000
1!
b10111010 $
b1000000000000000000000000 '
b111010100000011010110100110001110010100101000111001000100001 )
b1001 *
b1001 +
13
b10111010 6
b1000011100100100 8
b101001000100001 ;
b11010010110010010100001000001 <
b111000010111100000010000 =
b110001101001010001000100011011110000000100000000 >
b1000000000000000000000000 ?
b111010100000011010110100110001110010100101000111001000100001 @
b111010100000011010110100110001110010100101000111001000100001 A
b1000 B
b10110011 C
b1100 D
b1100 E
b1001 F

#330000
0!
03

#335000
1!
b11111010 $
b110001101001010001000100011011110000000100000000 '
b1000000000000000000000000 )
b1010 *
b1010 +
13
b11111010 6
b1111010000100100 8
b1000011100100100 ;
b1000111010101101111110100010000 <
b11010010110010010100001000001 =
b1010110110001110110011101000110111100001100110000010000001 >
b110001101001010001000100011011110000000100000000 ?
b1000000000000000000000000 @
b1000000000000000000000000 A
b1001 B
b1000 C
b1101 D
b1101 E
b1010 F

#340000
0!
03

#345000
1!
b1011000 $
b1010110110001110110011101000110111100001100110000010000001 '
b110001101001010001000100011011110000000100000000 )
b1011 *
b1011 +
13
b1011000 6
b1111001000000 8
b1111010000100100 ;
b11101000110101001010010100010000 <
b1000111010101101111110100010000 =
b1001111100001010111011110110111100000111010001010000100000000 >
b1010110110001110110011101000110111100001100110000010000001 ?
b110001101001010001000100011011110000000100000000 @
b110001101001010001000100011011110000000100000000 A
b1010 B
b111110 C
b1110 D
b1110 E
b1011 F

#350000
0!
03

#355000
1!
b10000001 $
b1001111100001010111011110110111100000111010001010000100000000 '
b1010110110001110110011101000110111100001100110000010000001 )
b1100 *
b1100 +
13
b10000001 6
b100000100000001 8
b1111001000000 ;
b11100100110001000000000000 <
b11101000110101001010010100010000 =
b1101001111000010000110111100111011001100111011011010000100000000 >
b1001111100001010111011110110111100000111010001010000100000000 ?
b1010110110001110110011101000110111100001100110000010000001 @
b1010110110001110110011101000110111100001100110000010000001 A
b1011 B
b10010001 C
b1111 D
b1111 E
b1100 F

#360000
0!
03

#365000
1!
b10101 $
b1101001111000010000110111100111011001100111011011010000100000000 '
b1001111100001010111011110110111100000111010001010000100000000 )
b1101 *
b1101 +
13
b10101 6
b110111001 8
b100000100000001 ;
b10000100000011000001000000001 <
b11100100110001000000000000 =
b1100110001101101101101100001000000000000000000000000 >
b1101001111000010000110111100111011001100111011011010000100000000 ?
b1001111100001010111011110110111100000111010001010000100000000 @
b1001111100001010111011110110111100000111010001010000100000000 A
b1100 B
b10111010 C
b10000 D
b10000 E
b1101 F

#370000
0!
03

#375000
1!
b11101011 $
b1100110001101101101101100001000000000000000000000000 '
b1101001111000010000110111100111011001100111011011010000100000000 )
b1110 *
b1110 +
13
b11101011 6
b1101011110111001 8
b110111001 ;
b101111011110110001 <
b10000100000011000001000000001 =
b100010000011100011100010001100111000001110000010000000001 >
b1100110001101101101101100001000000000000000000000000 ?
b1101001111000010000110111100111011001100111011011010000100000000 @
b1101001111000010000110111100111011001100111011011010000100000000 A
b1101 B
b11111010 C
b10001 D
b10001 E
b1110 F

#380000
0!
03

#385000
1!
b101 $
b100010000011100011100010001100111000001110000010000000001 '
b1100110001101101101101100001000000000000000000000000 )
b1111 *
b1111 +
13
b101 6
b11001 8
b1101011110111001 ;
b10110101110010000100001110110001 <
b101111011110110001 =
b100011001110011010110000100001100001 >
b100010000011100011100010001100111000001110000010000000001 ?
b1100110001101101101101100001000000000000000000000000 @
b1100110001101101101101100001000000000000000000000000 A
b1110 B
b1011000 C
b10010 D
b10010 E
b1111 F

#390000
0!
03

#395000
1!
b1010101 $
b100011001110011010110000100001100001 '
b100010000011100011100010001100111000001110000010000000001 )
b10000 *
b10000 +
13
b1010101 6
b1110000111001 8
b11001 ;
b1001110001 <
b10110101110010000100001110110001 =
b1000000100010100110011000110001000100000011101100010000001100001 >
b100011001110011010110000100001100001 ?
b100010000011100011100010001100111000001110000010000000001 @
b100010000011100011100010001100111000001110000010000000001 A
b1111 B
b10000001 C
b10011 D
b10011 E
b10000 F

#400000
0!
03

#405000
1!
b110 $
b1000000100010100110011000110001000100000011101100010000001100001 '
b100011001110011010110000100001100001 )
b10001 *
b10001 +
13
b110 6
b100100 8
b1110000111001 ;
b11000111001000010010110001 <
b1001110001 =
b1011111010111100001 >
b1000000100010100110011000110001000100000011101100010000001100001 ?
b100011001110011010110000100001100001 @
b100011001110011010110000100001100001 A
b10000 B
b10101 C
b10100 D
b10100 E
b10001 F

#410000
0!
03

#415000
1!
b10100101 $
b1011111010111100001 '
b1000000100010100110011000110001000100000011101100010000001100001 )
b10010 *
b10010 +
13
b10100101 6
b110101001011001 8
b100100 ;
b10100010000 <
b11000111001000010010110001 =
b1001101011100100100101110001011111110000001001100001 >
b1011111010111100001 ?
b1000000100010100110011000110001000100000011101100010000001100001 @
b1000000100010100110011000110001000100000011101100010000001100001 A
b10001 B
b11101011 C
b10101 D
b10101 E
b10010 F

#420000
0!
03

#425000
1!
b11000010 $
b1001101011100100100101110001011111110000001001100001 '
b1011111010111100001 )
b10011 *
b10011 +
13
b11000010 6
b1001001100000100 8
b110101001011001 ;
b101100001011011101001011110001 <
b10100010000 =
b110011010000100000000 >
b1001101011100100100101110001011111110000001001100001 ?
b1011111010111100001 @
b1011111010111100001 A
b10010 B
b101 C
b10110 D
b10110 E
b10011 F

#430000
0!
03

#435000
1!
b11010001 $
b110011010000100000000 '
b1001101011100100100101110001011111110000001001100001 )
b10100 *
b10100 +
13
b11010001 6
b1010101010100001 8
b1001001100000100 ;
b1010100011011011001100000010000 <
b101100001011011101001011110001 =
b11110011111110010001011011010101110100010100100011011100001 >
b110011010000100000000 ?
b1001101011100100100101110001011111110000001001100001 @
b1001101011100100100101110001011111110000001001100001 A
b10011 B
b1010101 C
b10111 D
b10111 E
b10100 F

#440000
0!
03

#445000
1!
b11001011 $
b11110011111110010001011011010101110100010100100011011100001 '
b110011010000100000000 )
b10101 *
b10101 +
13
b11001011 6
b1010000011111001 8
b1010101010100001 ;
b1110001101110100011100101000001 <
b1010100011011011001100000010000 =
b1101111011000000110101011010101010111111100110000000100000000 >
b11110011111110010001011011010101110100010100100011011100001 ?
b110011010000100000000 @
b110011010000100000000 A
b10100 B
b110 C
b11000 D
b11000 E
b10101 F

#450000
0!
03

#455000
1!
b11101000 $
b1101111011000000110101011010101010111111100110000000100000000 '
b11110011111110010001011011010101110100010100100011011100001 )
b10110 *
b10110 +
13
b11101000 6
b1101001001000000 8
b1010000011111001 ;
b1100101001110000011001000110001 <
b1110001101110100011100101000001 =
b11001010000101111011100000001010100001010000100000001010000001 >
b1101111011000000110101011010101010111111100110000000100000000 ?
b11110011111110010001011011010101110100010100100011011100001 @
b11110011111110010001011011010101110100010100100011011100001 A
b10101 B
b10100101 C
b11001 D
b11001 E
b10110 F

#460000
0!
03

#465000
1!
b11100 $
b11001010000101111011100000001010100001010000100000001010000001 '
b1101111011000000110101011010101010111111100110000000100000000 )
b10111 *
b10111 +
13
b11100 6
b1100010000 8
b1101001001000000 ;
b10101100101011010001000000000000 <
b1100101001110000011001000110001 =
b10100000000101011000111111000010101001010001110010110101100001 >
b11001010000101111011100000001010100001010000100000001010000001 ?
b1101111011000000110101011010101010111111100110000000100000000 @
b1101111011000000110101011010101010111111100110000000100000000 A
b10110 B
b11000010 C
b11010 D
b11010 E
b10111 F

#470000
0!
03

#475000
1!
b11111100 $
b10100000000101011000111111000010101001010001110010110101100001 '
b11001010000101111011100000001010100001010000100000001010000001 )
b11000 *
b11000 +
13
b11111100 6
b1111100000010000 8
b1100010000 ;
b10010110000100000000 <
b10101100101011010001000000000000 =
b111010001111001000000100111111010100001000000000000000000000000 >
b10100000000101011000111111000010101001010001110010110101100001 ?
b11001010000101111011100000001010100001010000100000001010000001 @
b11001010000101111011100000001010100001010000100000001010000001 A
b10111 B
b11010001 C
b11011 D
b11011 E
b11000 F

#480000
0!
03

#485000
1!
b11101101 $
b111010001111001000000100111111010100001000000000000000000000000 '
b10100000000101011000111111000010101001010001110010110101100001 )
b11001 *
b11001 +
13
b11101101 6
b1101101101101001 8
b1111100000010000 ;
b11110000010111110000000100000000 <
b10010110000100000000 =
b101011111110110110000010000000000000000 >
b111010001111001000000100111111010100001000000000000000000000000 ?
b10100000000101011000111111000010101001010001110010110101100001 @
b10100000000101011000111111000010101001010001110010110101100001 A
b11000 B
b11001011 C
b11100 D
b11100 E
b11001 F

#490000
0!
03

#495000
1!
b10111101 $
b101011111110110110000010000000000000000 '
b111010001111001000000100111111010100001000000000000000000000000 )
b11010 *
b11010 +
13
b10111101 6
b1000101110001001 8
b1101101101101001 ;
b10111100000011001101000100010001 <
b11110000010111110000000100000000 =
b1110000110110010010001010010000110111110000000010000000000000000 >
b101011111110110110000010000000000000000 ?
b111010001111001000000100111111010100001000000000000000000000000 @
b111010001111001000000100111111010100001000000000000000000000000 A
b11001 B
b11101000 C
b11101 D
b11101 E
b11010 F

#500000
0!
03

#505000
1!
b111111 $
b1110000110110010010001010010000110111110000000010000000000000000 '
b101011111110110110000010000000000000000 )
b11011 *
b11011 +
13
b111111 6
b111110000001 8
b1000101110001001 ;
b1001100000011100000111101010001 <
b10111100000011001101000100010001 =
b1000101000100010110100111011010100111100010101001100001100100001 >
b1110000110110010010001010010000110111110000000010000000000000000 ?
b101011111110110110000010000000000000000 @
b101011111110110110000010000000000000000 A
b11010 B
b11100 C
b11110 D
b11110 E
b11011 F

#510000
0!
03

#515000
1!
b10111100 $
b1000101000100010110100111011010100111100010101001100001100100001 '
b1110000110110010010001010010000110111110000000010000000000000000 )
b11100 *
b11100 +
13
b10111100 6
b1000101000010000 8
b111110000001 ;
b111100000101111100000001 <
b1001100000011100000111101010001 =
b1011010011000010110011101110111000101110001101001011110100001 >
b1000101000100010110100111011010100111100010101001100001100100001 ?
b1110000110110010010001010010000110111110000000010000000000000000 @
b1110000110110010010001010010000110111110000000010000000000000000 A
b11011 B
b11111100 C
b11111 D
b11111 E
b11100 F

#520000
0!
03

