Verilog/lab1_valid_interface/rtl/basic.v
//==============================================================================
// File name    : basic.v
// Description  : [Brief description of what this module does]
//
// Author       : [Jeongyoon Kang]
// Email        : [goneki9713@naver.com]
// Date         : 2025-12-13
// Version      : 1.0
//
// History:
//   2025-12-13 - [Jeongyoon Kang] - Initial version: Simple Vaild interface example
//
// Parameters:
//   PARAM_NAME  - [Description]
//
// Notes:
//   - [Any important notes about this module]
//   - [Design decisions, limitations, or usage guidelines]
//==============================================================================

`timescale 1ns/1ps
`default_nettype none

module power #(
    parameter DATA_WIDTH = 32
)(
    // Clock and Reset
    input  wire                     clk,
    input  wire                     reset_n,

    // Input Interface
    input  wire                     i_valid,
    input  wire  [DATA_WIDTH-1:0]   i_data,

    // Output Interface
    output wire                     o_valid,
    output wire  [63:0]   o_data
);

//🟩: Stage
//🟧: Combinational logic
//🟦: Sequential logic


//=============================================================================
// Internal Signal Declarations
//=============================================================================

//-----------------------------------------------------------------------------
// 🟩Stage 0
//-----------------------------------------------------------------------------
// 🟧Combinational signals (intermediate values, NOT registers)

    wire [63:0] power_of_2;

// 🟦Sequential signals (actual flip-flops)

    reg [2:0] r_valid;
    reg [63:0] r_power_of_2;

//-----------------------------------------------------------------------------
// 🟩Stage 1
//-----------------------------------------------------------------------------
// 🟧Combinational signals (intermediate values, NOT registers)

    wire [63:0] power_of_4;

// 🟦Sequential signals (actual flip-flops)

    // reg [2:0] r_valid;
    reg [63:0] r_power_of_4;

//-----------------------------------------------------------------------------
// 🟩Stage 2
//-----------------------------------------------------------------------------
// 🟧Combinational signals (intermediate values, NOT registers)

    wire [63:0] power_of_8;

// 🟦Sequential signals (actual flip-flops)

    // reg [2:0] r_valid;
    reg [63:0] r_power_of_8;



//=============================================================================
// 🟧Combinational Logic
//=============================================================================

// 🟩Stage 0

    assign power_of_2 = i_data * i_data;


// 🟩Stage 1

    assign power_of_4 = r_power_of_2 * r_power_of_2;


// 🟩Stage 2

    assign power_of_8 = r_power_of_4 * r_power_of_4;


//=============================================================================
// 🟦Sequential Logic (Registers)
//=============================================================================

// 🟩Stage 0

    //
    always@(posedge clk or negedge reset_n)begin
        if(!reset_n)begin
            r_valid[0] <= 1'b0; 
        end 
        else begin
            r_valid[0] <= i_valid;
        end
    end

    always@(posedge clk or negedge reset_n)begin
        if(!reset_n)begin
            r_power_of_2 <= 'b0;
        end
        else begin
            r_power_of_2 <= power_of_2;
        end
    end


// 🟩Stage 1

    always@(posedge clk or negedge reset_n)begin
        if(!reset_n)begin
            r_valid[1] <= 1'b0;
        end
        else begin
            r_valid[1] <= r_valid[0];
        end
    end

    always@(posedge clk or negedge reset_n)begin
        if(!reset_n)begin
            r_power_of_4 <= 'b0;
        end
        else begin
            r_power_of_4 <= power_of_4;
        end
    end


// 🟩Stage 2

    always@(posedge clk or negedge reset_n)begin
        if(!reset_n)begin
            r_valid[2] <= 1'b0;
        end
        else begin
            r_valid[2] <= r_valid[1];
        end
    end

    always@(posedge clk or negedge reset_n)begin
        if(!reset_n)begin
            r_power_of_8 <= 'b0;
        end
        else begin
            r_power_of_8 <= power_of_8;
        end
    end



//=============================================================================
// Output Assign(Must be registered output!)
//=============================================================================

    assign o_valid = r_valid[2];
    assign o_data = r_power_of_8;


//=============================================================================
// Assertions (for simulation/formal verification)
//=============================================================================
`ifdef FORMAL
    // Add formal properties here
`endif

`ifdef SIMULATION
    // Add simulation assertions here
`endif

endmodule

`default_nettype wire

Verilog/lab3_rtl_sim/testbench/case1a_tb.v
//==============================================================================
// File name    : case1a_tb.v
// Description  : Case 1A - Blocking assignment after @(posedge clk)
//
// Case Study: Assignment After Clock Edge - Blocking
//
// This testbench drives input signals using BLOCKING assignments immediately
// after waiting for the clock edge. The assignments occur in the Active region
// of the delta cycle, potentially causing race conditions with the DUT.
//
//==============================================================================

`timescale 1ns/1ps

module case1a_tb;

//=============================================================================
// Parameters
//=============================================================================
parameter DATA_WIDTH = 32;
parameter CLK_PERIOD = 10;

//=============================================================================
// Clock and Reset
//=============================================================================
reg clk;
reg reset_n;

//=============================================================================
// DUT Signals
//=============================================================================
reg                     i_valid_tb;
reg  [DATA_WIDTH-1:0]   i_data_tb;
wire                    o_valid_tb;
wire [63:0]             o_data_tb;

//=============================================================================
// Test Vectors
//=============================================================================
reg [DATA_WIDTH-1:0] test_values [0:4];
integer i;

//=============================================================================
// Clock Generation
//=============================================================================
initial begin
    clk = 0;
    forever #(CLK_PERIOD/2) clk = ~clk;
end

//=============================================================================
// DUT Instantiation
//=============================================================================
power #(
    .DATA_WIDTH(DATA_WIDTH)
) u_dut (
    .clk        (clk),
    .reset_n    (reset_n),
    .i_valid    (i_valid_tb),
    .i_data     (i_data_tb),
    .o_valid    (o_valid_tb),
    .o_data     (o_data_tb)
);

//=============================================================================
// Test Stimulus - Case 1A: BLOCKING after @(posedge clk)
//=============================================================================
initial begin
    // Initialize test vectors
    test_values[0] = 32'h00000002;
    test_values[1] = 32'h00000003;
    test_values[2] = 32'h00000005;
    test_values[3] = 32'h00000007;
    test_values[4] = 32'h0000000A;

    // Initialize signals
    i_valid_tb = 1'b0;
    i_data_tb = 32'h0;
    reset_n = 1'b0;

    // Wait for reset
    repeat(2) @(posedge clk);
    reset_n = 1'b1;
    repeat(1) @(posedge clk);

    $display("================================================================");
    $display("Case 1A: Blocking Assignment After Clock Edge");
    $display("================================================================");
    $display("Time\t\tEvent");
    $display("----------------------------------------------------------------");

    // Send test data using BLOCKING assignments AFTER @(posedge clk)
    for (i = 0; i < 5; i = i + 1) begin
        @(posedge clk);
        // BLOCKING assignments - occur in Active region immediately
        i_valid_tb = 1'b1;
        i_data_tb = test_values[i];
        $display("%0t ns\tAssigned i_data_tb = 0x%h (BLOCKING)", $time, test_values[i]);
    end

    // Deassert valid
    @(posedge clk);
    i_valid_tb = 1'b0;
    i_data_tb = 32'h0;

    // Wait for pipeline to flush
    repeat(5) @(posedge clk);

    $display("================================================================");
    $display("Simulation completed");
    $display("================================================================");
    $finish;
end

//=============================================================================
// Monitor outputs
//=============================================================================
initial begin
    $display("\nOutput Monitor:");
    $display("Time\t\to_valid\to_data");
    $display("----------------------------------------------------------------");
end

always @(posedge clk) begin
    if (o_valid_tb) begin
        $display("%0t ns\t%b\t0x%h", $time, o_valid_tb, o_data_tb);
    end
end

//=============================================================================
// Waveform Dump
//=============================================================================
initial begin
    $dumpfile("case1a.vcd");
    $dumpvars(0, case1a_tb);
end

endmodule

Verilog/lab3_rtl_sim/case1a.vcd
$date
   Sat Dec 27 21:05:57 2025
$end

$version
  2025.2
  $dumpfile ("case1a.vcd") 
$end

$timescale
  1ps
$end

$scope module case1a_tb $end
$var reg 1 ! clk $end
$var reg 1 " reset_n $end
$var reg 1 # i_valid_tb $end
$var reg 32 $ i_data_tb [31:0] $end
$var wire 1 % o_valid_tb $end
$var wire 64 & o_data_tb [63:0] $end
$var integer 32 ' i [31:0] $end
$scope module u_dut $end
$var wire 1 ( clk $end
$var wire 1 ) reset_n $end
$var wire 1 * i_valid $end
$var wire 32 + i_data [31:0] $end
$var wire 1 % o_valid $end
$var wire 64 & o_data [63:0] $end
$var wire 64 , power_of_2 [63:0] $end
$var reg 3 - r_valid [2:0] $end
$var reg 64 . r_power_of_2 [63:0] $end
$var wire 64 / power_of_4 [63:0] $end
$var reg 64 0 r_power_of_4 [63:0] $end
$var wire 64 1 power_of_8 [63:0] $end
$var reg 64 2 r_power_of_8 [63:0] $end
$upscope $end
$upscope $end
$enddefinitions $end

#0
$dumpvars
0!
0"
0#
b0 $
0%
b0 &
bx '
0(
0)
0*
b0 +
b0 ,
b0 -
b0 .
b0 /
b0 0
b0 1
b0 2
$end

#5000
1!
1(

#10000
0!
0(

#15000
1!
1"
1(
1)

#20000
0!
0(

#25000
1!
b0 '
1(

#30000
0!
0(

#35000
1!
1#
b10 $
b1 '
1(
1*
b10 +
b100 ,
b1 -

#40000
0!
0(

#45000
1!
b11 $
b10 '
1(
b11 +
b1001 ,
b11 -
b100 .
b10000 /

#50000
0!
0(

#55000
1!
b101 $
1%
b11 '
1(
b101 +
b11001 ,
b111 -
b1001 .
b1010001 /
b10000 0
b100000000 1

#60000
0!
0(

#65000
1!
b111 $
b100000000 &
b100 '
1(
b111 +
b110001 ,
b11001 .
b1001110001 /
b1010001 0
b1100110100001 1
b100000000 2

#70000
0!
0(

#75000
1!
b1010 $
b1100110100001 &
b101 '
1(
b1010 +
b1100100 ,
b110001 .
b100101100001 /
b1001110001 0
b1011111010111100001 1
b1100110100001 2

#80000
0!
0(

#85000
1!
0#
b0 $
b1011111010111100001 &
1(
0*
b0 +
b0 ,
b110 -
b1100100 .
b10011100010000 /
b100101100001 0
b10101111111011011000001 1
b1011111010111100001 2

#90000
0!
0(

#95000
1!
b10101111111011011000001 &
1(
b100 -
b0 .
b0 /
b10011100010000 0
b101111101011110000100000000 1
b10101111111011011000001 2

#100000
0!
0(

#105000
1!
0%
b101111101011110000100000000 &
1(
b0 -
b0 0
b0 1
b101111101011110000100000000 2

#110000
0!
0(

#115000
1!
b0 &
1(
b0 2

